xssa/__init__.py
xssa/credentials.py
xssa/catalog/__init__.py
xssa/providers/__init__.py
xssa/providers/optimus.py
xssa/providers/spacetrack.py
xssa/screening/__init__.py
xssa-0.1.0.dev0.dist-info/licenses/LICENSE
xssa-0.1.0.dev0.dist-info/METADATA
xssa-0.1.0.dev0.dist-info/WHEEL
xssa-0.1.0.dev0.dist-info/top_level.txt
xssa-0.1.0.dev0.dist-info/RECORD
